minimock.py
MiniMock-1.2.8.dist-info/DESCRIPTION.rst
MiniMock-1.2.8.dist-info/METADATA
MiniMock-1.2.8.dist-info/RECORD
MiniMock-1.2.8.dist-info/WHEEL
MiniMock-1.2.8.dist-info/metadata.json
MiniMock-1.2.8.dist-info/top_level.txt
MiniMock-1.2.8.dist-info/zip-safe
