Metadata-Version: 1.0
Name: MiniMock
Version: 1.2.8
Summary: The simplest possible mock library
Home-page: http://pypi.python.org/pypi/MiniMock
Author: Josh Bronson
Author-email: jabronson@gmail.com
License: MIT
Keywords: mock testing unittest
Platform: UNKNOWN
Classifier: Development Status :: 5 - Production/Stable
Classifier: License :: OSI Approved :: MIT License
Classifier: Topic :: Software Development :: Testing
Classifier: Programming Language :: Python
Classifier: Programming Language :: Python :: 2
Classifier: Programming Language :: Python :: 2.5
Classifier: Programming Language :: Python :: 2.6
Classifier: Programming Language :: Python :: 2.7
Classifier: Programming Language :: Python :: 3
